klsosdoids5/init.py
klsosdoids5/main.py
klsosdoids5-0.1.dist-info/METADATA
klsosdoids5-0.1.dist-info/WHEEL
klsosdoids5-0.1.dist-info/entry_points.txt
klsosdoids5-0.1.dist-info/top_level.txt
klsosdoids5-0.1.dist-info/RECORD
