Metadata-Version: 2.4
Name: klsosdoids5
Version: 0.1
Requires-Dist: requests
Dynamic: requires-dist
